colorlib/__init__.py
colorlib/boxes.py
colorlib/coloring.py
colorlib/text_manipulation.py
colorlib/typing.py
tui_colorlib-1.0.4.dist-info/METADATA
tui_colorlib-1.0.4.dist-info/WHEEL
tui_colorlib-1.0.4.dist-info/top_level.txt
tui_colorlib-1.0.4.dist-info/RECORD
