Metadata-Version: 2.1
Name: tui-colorlib
Version: 1.0.4
Summary: A library for creating a terminal user interface
Home-page: https://github.com/0x3C50/colorlib
Author: 0x150
Project-URL: Bug Tracker, https://github.com/0x3C50/colorlib/issues
Classifier: Programming Language :: Python :: 3
Classifier: License :: OSI Approved :: MIT License
Classifier: Operating System :: OS Independent
Requires-Python: >=3.6
